{
  "cards": [
    {
      "id": 1,
      "cert_number": "114913905",
      "name": "SLOWPOKE-REV.FOIL",
      "set": "POKEMON EX TEAM ROCKET RETURNS",
      "card_number": "76",
      "spec_number": "E582000094",
      "grade": "MINT 9",
      "grade_description": "MINT 9",
      "year": "2004",
      "brand": "POKEMON EX TEAM ROCKET RETURNS",
      "category": "TCG Cards",
      "variety": "TEAM ROCKET RETURNS",
      "label_type": "LighthouseLabel",
      "total_population": 62,
      "population_higher": 21,
      "is_dual_cert": false,
      "reverse_bar_code": true,
      "image_url": "https://d1htnxwo4o0jhw.cloudfront.net/cert/179383000/cSXAtJcA2Ua8hnbaFuM8sg.jpg",
      "image_front": "https://d1htnxwo4o0jhw.cloudfront.net/cert/179383000/cSXAtJcA2Ua8hnbaFuM8sg.jpg",
      "image_back": "https://d1htnxwo4o0jhw.cloudfront.net/cert/179383000/q4lD2DoCGU2ZKVohhA0kdw.jpg",
      "purchase_price": 0,
      "current_value": 0,
      "notes": "",
      "added_date": "2025-06-26"
    },
    {
      "id": 4,
      "cert_number": "114411512",
      "name": "LATIAS-HOLO",
      "set": "POKEMON EX DEOXYS",
      "card_number": "105",
      "spec_number": "F877000001",
      "grade": "EX-MT 6",
      "grade_description": "EX-MT 6",
      "year": "2005",
      "brand": "POKEMON EX DEOXYS",
      "category": "TCG Cards",
      "variety": "EX DEOXYS",
      "label_type": "LighthouseLabel",
      "total_population": 115,
      "population_higher": 518,
      "is_dual_cert": false,
      "reverse_bar_code": true,
      "image_url": "https://d1htnxwo4o0jhw.cloudfront.net/cert/179085377/N9w-2AcV5UOLpVBrizveUg.jpg",
      "image_front": "https://d1htnxwo4o0jhw.cloudfront.net/cert/179085377/N9w-2AcV5UOLpVBrizveUg.jpg",
      "image_back": "https://d1htnxwo4o0jhw.cloudfront.net/cert/179085377/VzcUUyPRM0yTPdDnzFTfWA.jpg",
      "purchase_price": 0,
      "current_value": 0,
      "notes": "",
      "added_date": "2025-06-26"
    },
    {
      "id": 5,
      "cert_number": "106966067",
      "name": "TREECKO-HOLO",
      "set": "POKEMON EX TEAM ROCKET RETURNS",
      "card_number": "109",
      "spec_number": "E582000004",
      "grade": "EX-MT 6",
      "grade_description": "EX-MT 6",
      "year": "2004",
      "brand": "POKEMON EX TEAM ROCKET RETURNS",
      "category": "TCG Cards",
      "variety": "EX TEAM ROCKET RETURNS",
      "label_type": "LighthouseLabel",
      "total_population": 87,
      "population_higher": 649,
      "is_dual_cert": false,
      "reverse_bar_code": true,
      "image_url": "https://d1htnxwo4o0jhw.cloudfront.net/cert/174277784/DrJHmICXFkqnxFL9I51ehA.jpg",
      "image_front": "https://d1htnxwo4o0jhw.cloudfront.net/cert/174277784/DrJHmICXFkqnxFL9I51ehA.jpg",
      "image_back": "https://d1htnxwo4o0jhw.cloudfront.net/cert/174277784/CDieF0d_sEOCy3KyYRxqtg.jpg",
      "purchase_price": 0,
      "current_value": 0,
      "notes": "",
      "added_date": "2025-06-26"
    },
    {
      "id": 6,
      "cert_number": "82459363",
      "name": "MUDKIP-HOLO",
      "set": "POKEMON EX TEAM ROCKET RETURNS",
      "card_number": "107",
      "spec_number": "E582000012",
      "grade": "NM-MT 8",
      "grade_description": "NM-MT 8",
      "year": "2004",
      "brand": "POKEMON EX TEAM ROCKET RETURNS",
      "category": "TCG Cards",
      "variety": "EX TEAM ROCKET RETURNS",
      "label_type": "LighthouseLabel",
      "total_population": 201,
      "population_higher": 315,
      "is_dual_cert": false,
      "reverse_bar_code": true,
      "image_url": "https://d1htnxwo4o0jhw.cloudfront.net/cert/147868772/NSnyU1ruWUaOET7dEJPDqQ.jpg",
      "image_front": "https://d1htnxwo4o0jhw.cloudfront.net/cert/147868772/NSnyU1ruWUaOET7dEJPDqQ.jpg",
      "image_back": "https://d1htnxwo4o0jhw.cloudfront.net/cert/147868772/pLCO0H7dVUGQSyyt1OFnqg.jpg",
      "purchase_price": 0,
      "current_value": 0,
      "notes": "",
      "added_date": "2025-06-26"
    },
    {
      "id": 7,
      "cert_number": "63734553",
      "name": "TORCHIC-HOLO",
      "set": "POKEMON EX TEAM ROCKET RETURNS",
      "card_number": "108",
      "spec_number": "E582000006",
      "grade": "NM-MT 8",
      "grade_description": "NM-MT 8",
      "year": "2004",
      "brand": "POKEMON EX TEAM ROCKET RETURNS",
      "category": "TCG Cards",
      "variety": "EX TEAM ROCKET RETURNS",
      "label_type": "LighthouseLabel",
      "total_population": 213,
      "population_higher": 246,
      "is_dual_cert": false,
      "reverse_bar_code": true,
      "image_url": "https://d1htnxwo4o0jhw.cloudfront.net/cert/126468872/356302812.jpg",
      "image_front": "https://d1htnxwo4o0jhw.cloudfront.net/cert/126468872/356302812.jpg",
      "image_back": "https://d1htnxwo4o0jhw.cloudfront.net/cert/126468872/356305507.jpg",
      "purchase_price": 0,
      "current_value": 0,
      "notes": "",
      "added_date": "2025-06-26"
    },
    {
      "id": 8,
      "cert_number": "105274270",
      "name": "RAYQUAZA-HOLO",
      "set": "POKEMON EX DEOXYS",
      "card_number": "107",
      "spec_number": "F877000002",
      "grade": "EX-MT 6",
      "grade_description": "EX-MT 6",
      "year": "2005",
      "brand": "POKEMON EX DEOXYS",
      "category": "TCG Cards",
      "variety": "EX DEOXYS",
      "label_type": "LighthouseLabel",
      "total_population": 143,
      "population_higher": 672,
      "is_dual_cert": false,
      "reverse_bar_code": true,
      "image_url": "https://d1htnxwo4o0jhw.cloudfront.net/cert/173361196/iRoFi7FWckKkpmVPxrgI5Q_ce24b.jpg",
      "image_front": "https://d1htnxwo4o0jhw.cloudfront.net/cert/173361196/iRoFi7FWckKkpmVPxrgI5Q_ce24b.jpg",
      "image_back": "https://d1htnxwo4o0jhw.cloudfront.net/cert/173361196/fvJgvy6EqEmfa8Yk-3mYJA.jpg",
      "purchase_price": 0,
      "current_value": 0,
      "notes": "",
      "added_date": "2025-06-26"
    },
    {
      "id": 9,
      "cert_number": "108528310",
      "name": "KYOGRE-HOLO",
      "set": "POKEMON EX DELTA SPECIES",
      "card_number": "112",
      "spec_number": "G267000004",
      "grade": "EX-MT 6",
      "grade_description": "EX-MT 6",
      "year": "2005",
      "brand": "POKEMON EX DELTA SPECIES",
      "category": "TCG Cards",
      "variety": "EX DELTA SPECIES",
      "label_type": "LighthouseLabel",
      "total_population": 96,
      "population_higher": 689,
      "is_dual_cert": false,
      "reverse_bar_code": true,
      "image_url": "https://d1htnxwo4o0jhw.cloudfront.net/cert/175463558/3KAV8hobski0loWaBjO1gQ.jpg",
      "image_front": "https://d1htnxwo4o0jhw.cloudfront.net/cert/175463558/3KAV8hobski0loWaBjO1gQ.jpg",
      "image_back": "https://d1htnxwo4o0jhw.cloudfront.net/cert/175463558/fkigJab48UKk3P54PlszMw.jpg",
      "purchase_price": 0,
      "current_value": 0,
      "notes": "",
      "added_date": "2025-06-27"
    },
    {
      "id": 10,
      "cert_number": "110644666",
      "name": "REGISTEEL-HOLO",
      "set": "POKEMON EX LEGEND MAKER",
      "card_number": "92",
      "spec_number": "P057000001",
      "grade": "EX-MT 6",
      "grade_description": "EX-MT 6",
      "year": "2006",
      "brand": "POKEMON EX LEGEND MAKER",
      "category": "TCG Cards",
      "variety": "EX LEGEND MAKER",
      "label_type": "LighthouseLabel",
      "total_population": 108,
      "population_higher": 696,
      "is_dual_cert": false,
      "reverse_bar_code": true,
      "image_url": "https://d1htnxwo4o0jhw.cloudfront.net/cert/176817657/4pvTWBS5okyIfjkGccnSCg.jpg",
      "image_front": "https://d1htnxwo4o0jhw.cloudfront.net/cert/176817657/4pvTWBS5okyIfjkGccnSCg.jpg",
      "image_back": "https://d1htnxwo4o0jhw.cloudfront.net/cert/176817657/anUcEdXdtEGEElpTDRnWWQ.jpg",
      "purchase_price": 0,
      "current_value": 0,
      "notes": "",
      "added_date": "2025-06-27"
    },
    {
      "id": 11,
      "cert_number": "102547203",
      "name": "TORCHIC-HOLO",
      "set": "POKEMON BLACK STAR PROMO",
      "card_number": "006",
      "spec_number": "OW86000004",
      "grade": "NM 7",
      "grade_description": "NM 7",
      "year": "2004",
      "brand": "POKEMON BLACK STAR PROMO",
      "category": "TCG Cards",
      "variety": "PROMO-EUR.POP TOURNAMENT",
      "label_type": "LighthouseLabel",
      "total_population": 49,
      "population_higher": 78,
      "is_dual_cert": false,
      "reverse_bar_code": true,
      "image_url": "https://d1htnxwo4o0jhw.cloudfront.net/cert/171169706/Ib8IXqnFVkCmpp57NsALpw.jpg",
      "image_front": "https://d1htnxwo4o0jhw.cloudfront.net/cert/171169706/Ib8IXqnFVkCmpp57NsALpw.jpg",
      "image_back": "https://d1htnxwo4o0jhw.cloudfront.net/cert/171169706/Z0kdTXHtOU-N5lBrh8PodQ.jpg",
      "purchase_price": 0,
      "current_value": 0,
      "notes": "",
      "added_date": "2025-06-27"
    },
    {
      "id": 12,
      "cert_number": "102547202",
      "name": "MUDKIP-HOLO",
      "set": "POKEMON BLACK STAR PROMO",
      "card_number": "005",
      "spec_number": "OW86000022",
      "grade": "NM-MT 8",
      "grade_description": "NM-MT 8",
      "year": "2004",
      "brand": "POKEMON BLACK STAR PROMO",
      "category": "TCG Cards",
      "variety": "PROMO-EUR.POP TOURNAMENT",
      "label_type": "LighthouseLabel",
      "total_population": 45,
      "population_higher": 56,
      "is_dual_cert": false,
      "reverse_bar_code": true,
      "image_url": "https://d1htnxwo4o0jhw.cloudfront.net/cert/171169705/jbpaEP6cs0KePWRfqViUIw.jpg",
      "image_front": "https://d1htnxwo4o0jhw.cloudfront.net/cert/171169705/jbpaEP6cs0KePWRfqViUIw.jpg",
      "image_back": "https://d1htnxwo4o0jhw.cloudfront.net/cert/171169705/QKTjNWKZPUiX43mDZg4v5w.jpg",
      "purchase_price": 0,
      "current_value": 0,
      "notes": "",
      "added_date": "2025-06-27"
    },
    {
      "id": 17,
      "cert_number": "116622002",
      "name": "REGIROCK-HOLO",
      "set": "POKEMON EX LEGEND MAKER",
      "card_number": "91",
      "spec_number": "P057000002",
      "grade": "EX-MT 6",
      "grade_description": "EX-MT 6",
      "year": "2006",
      "brand": "POKEMON EX LEGEND MAKER",
      "category": "TCG Cards",
      "variety": "EX LEGEND MAKER",
      "label_type": "LighthouseLabel",
      "total_population": 118,
      "population_higher": 665,
      "is_dual_cert": false,
      "reverse_bar_code": true,
      "image_url": "https://d1htnxwo4o0jhw.cloudfront.net/cert/180535649/KaTaWGo2CkCjPTzBaKXtZw.jpg",
      "image_front": "https://d1htnxwo4o0jhw.cloudfront.net/cert/180535649/KaTaWGo2CkCjPTzBaKXtZw.jpg",
      "image_back": "https://d1htnxwo4o0jhw.cloudfront.net/cert/180535649/mANRwcKTYUykRkYnVxxt5A.jpg",
      "purchase_price": 0,
      "current_value": 0,
      "notes": "",
      "added_date": "2025-07-01"
    },
    {
      "id": 18,
      "cert_number": "109123882",
      "name": "TORCHIC-HOLO",
      "set": "POKEMON BLACK STAR PROMO",
      "card_number": "017",
      "spec_number": "OW86000005",
      "grade": "NM 7",
      "grade_description": "NM 7",
      "year": "2004",
      "brand": "POKEMON BLACK STAR PROMO",
      "category": "TCG Cards",
      "variety": "PROMO-EX DECK TINS",
      "label_type": "LighthouseLabel",
      "total_population": 24,
      "population_higher": 56,
      "is_dual_cert": false,
      "reverse_bar_code": true,
      "image_url": "https://d1htnxwo4o0jhw.cloudfront.net/cert/175804341/OvTTRaN4cEuiutSfWpU7Pg.jpg",
      "image_front": "https://d1htnxwo4o0jhw.cloudfront.net/cert/175804341/OvTTRaN4cEuiutSfWpU7Pg.jpg",
      "image_back": "https://d1htnxwo4o0jhw.cloudfront.net/cert/175804341/hWen-QOij0OQqGqahYDBPA.jpg",
      "purchase_price": 0,
      "current_value": 0,
      "notes": "",
      "added_date": "2025-07-01"
    }
  ],
  "next_id": 19,
  "last_updated": "2025-07-01 19:37:28"
}